kml2geojson/__init__.py
kml2geojson/cli.py
kml2geojson/main.py
kml2geojson-5.0.1.dist-info/entry_points.txt
kml2geojson-5.0.1.dist-info/LICENSE.txt
kml2geojson-5.0.1.dist-info/WHEEL
kml2geojson-5.0.1.dist-info/METADATA
kml2geojson-5.0.1.dist-info/RECORD
